{
  "sich erholen": "to recover",
  "essen": "to eat",
  "trinken": "to drink",
  "vorbereiten": "to prepare",
  "sich vorstellen": "to introduce oneself",
  "schlafen": "to sleep",
  "sich unterhalten": "to support",
  "werden": "to become",
  "w채hrend": "while",
  "vollst채ndig": "completely",
  "der Unfall": "accident",
  "die Chirurgie": "surgery",
  "sich aufregen": "to get irritated",
  "die Ged채nke": "thoughts",
  "der Gedanke": "thought",
  "sich vergn체gen": "to enjoy oneself",
  "sich beeilen": "to hurry up",
  "wegen": "because of",
  "verzeihen": "to forgive"
}